highlighter/__init__.py
highlighter/py.typed
highlighter/sdist.py
highlighter/types.py
highlighter/tests/__init__.py
highlighter/tests/__main__.py
highlighter/tests/sdist.py
highlighter/tests/types.py
highlighter-0.2.0.dist-info/LICENSE
highlighter-0.2.0.dist-info/METADATA
highlighter-0.2.0.dist-info/WHEEL
highlighter-0.2.0.dist-info/top_level.txt
highlighter-0.2.0.dist-info/RECORD
