Metadata-Version: 2.1
Name: highlighter
Version: 0.2.0
Summary: Easy-to-use PEP 508 markers
Home-page: https://github.com/python-packaging/highlighter
Author: Tim Hatch
Author-email: tim@timhatch.com
License: MIT
Requires-Python: >=3.10
Provides-Extra: dev
Provides-Extra: test
License-File: LICENSE
